{
  "meta": {
    "svg_source": "target_.web-cloud.hosting.clouddb.svg",
    "html_target": "/static/web-cloud/hosting/clouddb.html",
    "section": "web-cloud",
    "subsection": "hosting",
    "page": "clouddb",
    "title": "Clouddb",
    "last_updated": "2025-12-30T09:31:03.253241"
  },
  "nav1": {
    "active": "Web Cloud",
    "items": [
      {
        "label": "Web Cloud",
        "url": "/static/web-cloud/index.html",
        "x": 510,
        "y": 32
      }
    ]
  },
  "nav2": {
    "active": "Hosting",
    "items": [
      {
        "label": "Hébergement",
        "url": "/static/web-cloud/hosting/general.html",
        "x": 240,
        "y": 75
      }
    ]
  },
  "actions": [
    {
      "label": "+ Commander une Cloud Database",
      "type": "add",
      "x": 116.0,
      "y": 121.0,
      "class": "text-primary",
      "url": "#"
    }
  ],
  "sidebar": {
    "type": "hosting-list",
    "clickable": false,
    "note": "Liste - selection locale uniquement"
  }
}