{
  "meta": {
    "svg_source": "target_.bare-metal.nasha.modal-delete-snapshot.svg",
    "html_target": "/static/bare-metal/nasha/modal-delete-snapshot.html",
    "section": "bare-metal",
    "subsection": "nasha",
    "page": "modal-delete-snapshot",
    "title": "Modal Delete Snapshot",
    "last_updated": "2025-12-29T23:35:52.319293"
  },
  "nav1": {
    "active": "Web Cloud",
    "items": []
  },
  "nav2": {
    "active": "Nasha",
    "items": []
  },
  "actions": [
    {
      "label": "Supprimer un snapshot",
      "type": "danger",
      "x": 24.0,
      "y": 38.0,
      "class": "text-heading",
      "url": "#"
    },
    {
      "label": "Fermer",
      "type": "close",
      "x": 30.0,
      "y": 26.0,
      "class": "text-body",
      "url": "/static/web-cloud/nasha/general.html"
    },
    {
      "label": "Supprimer le snapshot",
      "type": "danger",
      "x": 15.0,
      "y": 26.0,
      "class": "text-white",
      "url": "#"
    }
  ],
  "sidebar": {
    "type": "nasha-list",
    "clickable": false,
    "note": "Liste - selection locale uniquement"
  }
}