{
  "meta": {
    "svg_source": "target_.web-cloud.voip.carrier-sip.endpoints.svg",
    "html_target": "/static/web-cloud/voip/carrier-sip/endpoints.html",
    "section": "web-cloud",
    "subsection": "voip",
    "page": "carrier-sip.endpoints",
    "title": "Endpoints Carrier SIP",
    "last_updated": "2025-12-30T10:00:00"
  },
  "nav1": {
    "active": "Web Cloud",
    "items": [{"label": "Web Cloud", "url": "/static/web-cloud/index.html", "x": 510, "y": 32}]
  },
  "nav2": {
    "active": "VoIP",
    "items": [{"label": "VoIP", "url": "/static/web-cloud/voip/index.html", "x": 500, "y": 75}]
  },
  "nav3": {
    "active": "Endpoints",
    "items": [
      {"label": "Dashboard", "url": "/static/web-cloud/voip/carrier-sip/dashboard.html"},
      {"label": "Endpoints", "url": "/static/web-cloud/voip/carrier-sip/endpoints.html"},
      {"label": "CDR", "url": "/static/web-cloud/voip/carrier-sip/cdr.html"},
      {"label": "Routage", "url": "/static/web-cloud/voip/carrier-sip/routing.html"},
      {"label": "Parametres", "url": "/static/web-cloud/voip/carrier-sip/settings.html"}
    ]
  },
  "actions": [
    {"label": "+ Ajouter", "type": "add", "x": 980, "y": 315, "url": "/static/web-cloud/voip/modal/endpoint-add.html"},
    {"label": "Modifier", "type": "edit", "x": 956, "y": 410, "url": "/static/web-cloud/voip/modal/endpoint-edit.html"},
    {"label": "x", "type": "delete", "x": 1016, "y": 410, "url": "#"},
    {"label": "Copier", "type": "copy", "x": 266, "y": 354, "url": "#"}
  ]
}
