{
  "meta": {
    "svg_source": "target_.home.support.modal-close-ticket.svg",
    "html_target": "/static/home/support/modal-close-ticket.html",
    "section": "home",
    "subsection": "support",
    "page": "modal-close-ticket",
    "title": "Modal Close Ticket",
    "last_updated": "2025-12-29T23:35:55.851025"
  },
  "nav1": {
    "active": "Web Cloud",
    "items": []
  },
  "nav2": {
    "active": "Support",
    "items": []
  },
  "actions": [
    {
      "label": "Annuler",
      "type": "cancel",
      "x": 40.0,
      "y": 26.0,
      "class": "text-body",
      "url": "/static/web-cloud/support/general.html"
    }
  ],
  "sidebar": {
    "type": "support-list",
    "clickable": false,
    "note": "Liste - selection locale uniquement"
  }
}