{
  "meta": {
    "svg_source": "target_.web-cloud.wordpress.modal-create.svg",
    "html_target": "/static/web-cloud/wordpress/modal-create.html",
    "section": "web-cloud",
    "subsection": "wordpress",
    "page": "modal-create",
    "title": "Créer un site WordPress",
    "parent_page": "/static/web-cloud/wordpress/index.html",
    "last_updated": "2025-12-30T13:00:00"
  },
  "modal_buttons": [
    {"label": "×", "type": "close", "x": 760, "y": 38, "url": "/static/web-cloud/wordpress/index.html"},
    {"label": "Annuler", "type": "cancel", "x": 50, "y": 23, "url": "/static/web-cloud/wordpress/index.html"},
    {"label": "Créer le site", "type": "submit", "x": 652, "y": 23, "url": "/static/web-cloud/wordpress/tasks.html"}
  ]
}
