{
  "meta": {
    "svg_source": "target_.network.load-balancer.svg",
    "html_target": "/static/network/load-balancer/load-balancer.html",
    "section": "network",
    "subsection": "load-balancer",
    "page": "load-balancer",
    "title": "Load Balancer",
    "last_updated": "2025-12-29T23:35:59.749061"
  },
  "nav1": {
    "active": "Web Cloud",
    "items": []
  },
  "nav2": {
    "active": "Load Balancer",
    "items": []
  },
  "actions": [
    {
      "label": "Commander",
      "type": "order",
      "x": 20.0,
      "y": 103.0,
      "class": "text-primary",
      "url": "#"
    },
    {
      "label": "Voir les détails de mon service",
      "type": "view",
      "x": 16.0,
      "y": 30.0,
      "class": "text-body",
      "url": "#"
    }
  ],
  "sidebar": {
    "type": "load-balancer-list",
    "clickable": false,
    "note": "Liste - selection locale uniquement"
  }
}