{
  "meta": {
    "svg_source": "target_.public-cloud.ai-tools.tab-datastore.svg",
    "html_target": "/static/public-cloud/ai-tools/tab-datastore.html",
    "section": "public-cloud",
    "subsection": "ai-tools",
    "page": "tab-datastore",
    "title": "Tab Datastore",
    "last_updated": "2025-12-29T23:30:03.342593"
  },
  "nav1": {
    "active": "Web Cloud",
    "items": []
  },
  "nav2": {
    "active": "Ai Tools",
    "items": []
  },
  "actions": [
    {
      "label": "Pour créer votre datastore S3, vous devez être en mesure de renseigner l'access_key et la secret_key.",
      "type": "button",
      "x": 15.0,
      "y": 45.0,
      "class": "text-primary",
      "url": "#"
    },
    {
      "label": "Gérer mes utilisateurs S3 →",
      "type": "link",
      "x": 900.0,
      "y": 35.0,
      "class": "text-primary",
      "url": "#"
    },
    {
      "label": "+ Configurer un datastore S3",
      "type": "add",
      "x": 40.0,
      "y": 213.0,
      "class": "text-white",
      "url": "#"
    },
    {
      "label": "Modifier",
      "type": "edit",
      "x": 15.0,
      "y": 30.0,
      "class": "text-body",
      "url": "#"
    },
    {
      "label": "Supprimer",
      "type": "delete",
      "x": 15.0,
      "y": 70.0,
      "class": "",
      "url": "#"
    }
  ],
  "sidebar": {
    "type": "ai-tools-list",
    "clickable": false,
    "note": "Liste - selection locale uniquement"
  }
}