{
  "meta": {
    "svg_source": "target_.web-cloud.hebergement.hosting.cdn.svg",
    "html_target": "/static/web-cloud/hebergement/hosting/cdn.html",
    "section": "web-cloud",
    "subsection": "hosting",
    "page": "cdn",
    "title": "Cdn",
    "last_updated": "2025-12-30T09:31:03.245316"
  },
  "nav1": {
    "active": "Web Cloud",
    "items": [
      {
        "label": "Web Cloud",
        "url": "/static/web-cloud/index.html",
        "x": 510,
        "y": 32
      }
    ]
  },
  "nav2": {
    "active": "Hosting",
    "items": [
      {
        "label": "Hebergement",
        "url": "/static/web-cloud/hosting/general.html",
        "x": 240,
        "y": 75
      }
    ]
  },
  "nav3": {
    "active": "CDN",
    "items": [
      {
        "label": "CDN",
        "url": "/static/web-cloud/hosting/cdn.html"
      }
    ]
  },
  "actions": [
    {
      "label": "Vider le cache",
      "type": "clear",
      "x": 960.0,
      "y": 69.0,
      "class": "text-primary",
      "url": "#"
    }
  ],
  "sidebar": {
    "type": "hosting-list",
    "clickable": false,
    "note": "Liste - selection locale uniquement"
  }
}