{
  "meta": {
    "svg_source": "target_.bare-metal.ip.modal-firewall-game-rule-delete.svg",
    "html_target": "/static/bare-metal/ip/modal-firewall-game-rule-delete.html",
    "section": "bare-metal",
    "subsection": "ip",
    "page": "modal-firewall-game-rule-delete",
    "title": "Modal Firewall Game Rule Delete",
    "last_updated": "2025-12-29T23:35:52.208558"
  },
  "nav1": {
    "active": "Web Cloud",
    "items": []
  },
  "nav2": {
    "active": "Ip",
    "items": []
  },
  "actions": [
    {
      "label": "Supprimer la règle",
      "type": "danger",
      "x": 80.0,
      "y": 62.0,
      "class": "",
      "url": "#"
    },
    {
      "label": "Annuler",
      "type": "cancel",
      "x": 25.0,
      "y": 23.0,
      "class": "",
      "url": "/static/web-cloud/ip/general.html"
    },
    {
      "label": "Supprimer",
      "type": "danger",
      "x": 25.0,
      "y": 23.0,
      "class": "",
      "url": "#"
    }
  ],
  "sidebar": {
    "type": "ip-list",
    "clickable": false,
    "note": "Liste - selection locale uniquement"
  }
}