{
  "meta": {
    "svg_source": "target_.web-cloud.access.general.svg",
    "html_target": "/static/web-cloud/access/general.html",
    "section": "web-cloud",
    "subsection": "access",
    "page": "general",
    "title": "General",
    "last_updated": "2025-12-30T09:46:46.065044"
  },
  "nav1": {
    "active": "Web Cloud",
    "items": [
      {
        "label": "Accueil",
        "url": "/static/index.html",
        "x": 40,
        "y": 32
      },
      {
        "label": "Public Cloud",
        "url": "/static/public-cloud/index.html",
        "x": 110,
        "y": 32
      },
      {
        "label": "Hosted Private Cloud",
        "url": "/static/private-cloud/index.html",
        "x": 210,
        "y": 32
      },
      {
        "label": "Bare Metal Cloud",
        "url": "/static/bare-metal/index.html",
        "x": 370,
        "y": 32
      },
      {
        "label": "Web Cloud",
        "url": "/static/web-cloud/index.html",
        "x": 510,
        "y": 32
      },
      {
        "label": "Network",
        "url": "/static/network/index.html",
        "x": 620,
        "y": 32
      },
      {
        "label": "IAM / Securite",
        "url": "/static/iam/index.html",
        "x": 700,
        "y": 32
      },
      {
        "label": "Licences",
        "url": "/static/license/index.html",
        "x": 810,
        "y": 32
      }
    ]
  },
  "nav2": {
    "active": "Accès",
    "items": [
      {
        "label": "Accueil",
        "url": "/static/web-cloud/index.html",
        "x": 40,
        "y": 75
      },
      {
        "label": "Domaines et DNS",
        "url": "/static/web-cloud/domain/index.html",
        "x": 110,
        "y": 75
      },
      {
        "label": "Hebergement",
        "url": "/static/web-cloud/hosting/general.html",
        "x": 240,
        "y": 75
      },
      {
        "label": "Wordpress",
        "url": "/static/web-cloud/wordpress/index.html",
        "x": 345,
        "y": 75
      },
      {
        "label": "Emails",
        "url": "/static/web-cloud/emails/index.html",
        "x": 430,
        "y": 75
      },
      {
        "label": "VoIP",
        "url": "/static/web-cloud/voip/lines/general.html",
        "x": 500,
        "y": 75
      },
      {
        "label": "Acces",
        "url": "/static/web-cloud/access/index.html",
        "x": 550,
        "y": 75
      }
    ]
  },
  "nav3": {
    "active": "General",
    "items": [
      {
        "label": "General",
        "url": "/static/web-cloud/access/general.html"
      },
      {
        "label": "Ligne",
        "url": "/static/web-cloud/access/line.html"
      },
      {
        "label": "Modem",
        "url": "/static/web-cloud/access/modem-ovh.html"
      },
      {
        "label": "Services",
        "url": "/static/web-cloud/access/services.html"
      },
      {
        "label": "VoIP",
        "url": "/static/web-cloud/access/voip.html"
      },
      {
        "label": "Options",
        "url": "/static/web-cloud/access/options.html"
      },
      {
        "label": "Taches",
        "url": "/static/web-cloud/access/tasks.html"
      }
    ]
  },
  "actions": [
    {
      "label": "Guides",
      "type": "external",
      "x": 1350.0,
      "y": 75.0,
      "class": "text-primary",
      "url": "/static/lien_externe.html"
    },
    {
      "label": "Configurer →",
      "type": "link",
      "x": 440.0,
      "y": 110.0,
      "class": "text-primary",
      "url": "/static/web-cloud/access/modem-ovh.html"
    },
    {
      "label": "Gerer →",
      "type": "link",
      "x": 440.0,
      "y": 120.0,
      "class": "text-primary",
      "url": "/static/web-cloud/access/general.html"
    },
    {
      "label": "✓ IP fixe",
      "type": "check",
      "x": 55.0,
      "y": 67.0,
      "class": "",
      "url": "/static/page_manquante.html"
    },
    {
      "label": "✓ IPv6",
      "type": "check",
      "x": 130.0,
      "y": 67.0,
      "class": "",
      "url": "/static/page_manquante.html"
    },
    {
      "label": "✓ GTR 4h",
      "type": "check",
      "x": 205.0,
      "y": 67.0,
      "class": "",
      "url": "/static/page_manquante.html"
    },
    {
      "label": "+ Ajouter",
      "type": "add",
      "x": 440.0,
      "y": 70.0,
      "class": "text-primary",
      "url": "/static/page_manquante.html"
    },
    {
      "label": "Gerer IPs →",
      "type": "link",
      "x": 420.0,
      "y": 60.0,
      "class": "text-primary",
      "url": "/static/page_manquante.html"
    },
    {
      "label": "→",
      "type": "link",
      "x": 210.0,
      "y": 60.0,
      "class": "text-primary",
      "url": "/static/page_manquante.html"
    },
    {
      "label": "→",
      "type": "link",
      "x": 480.0,
      "y": 60.0,
      "class": "text-primary",
      "url": "/static/page_manquante.html"
    },
    {
      "label": "Configurer WiFi",
      "type": "config",
      "x": 560.0,
      "y": 55.0,
      "class": "text-dark",
      "url": "/static/page_manquante.html"
    },
    {
      "label": "→",
      "type": "link",
      "x": 750.0,
      "y": 60.0,
      "class": "text-primary",
      "url": "/static/page_manquante.html"
    },
    {
      "label": "Modifier mot de passe",
      "type": "edit",
      "x": 830.0,
      "y": 55.0,
      "class": "text-dark",
      "url": "/static/page_manquante.html"
    },
    {
      "label": "→",
      "type": "link",
      "x": 1016.0,
      "y": 60.0,
      "class": "text-primary",
      "url": "/static/page_manquante.html"
    }
  ],
  "sidebar": {
    "type": "access-list",
    "clickable": false,
    "note": "Liste - selection locale uniquement"
  }
}