{
  "meta": {
    "svg_source": "target_.bare-metal.dedicated.wizard-bandwidth-public-order.svg",
    "html_target": "/static/bare-metal/dedicated/wizard-bandwidth-public-order.html",
    "section": "bare-metal",
    "subsection": "dedicated",
    "page": "wizard-bandwidth-public-order",
    "title": "Wizard Bandwidth Public Order",
    "last_updated": "2025-12-29T23:35:52.175505"
  },
  "nav1": {
    "active": "Web Cloud",
    "items": []
  },
  "nav2": {
    "active": "Dedicated",
    "items": []
  },
  "actions": [
    {
      "label": "Commander de la bande passante",
      "type": "order",
      "x": 75.0,
      "y": 65.0,
      "class": "",
      "url": "#"
    }
  ],
  "sidebar": {
    "type": "dedicated-list",
    "clickable": false,
    "note": "Liste - selection locale uniquement"
  }
}