{
  "meta": {
    "svg_source": "target_.home.account.modal-u2f-delete.svg",
    "html_target": "/static/home/account/modal-u2f-delete.html",
    "section": "home",
    "subsection": "account",
    "page": "modal-u2f-delete",
    "title": "Modal U2F Delete",
    "last_updated": "2025-12-29T23:35:55.639518"
  },
  "nav1": {
    "active": "Web Cloud",
    "items": []
  },
  "nav2": {
    "active": "Account",
    "items": []
  },
  "actions": [
    {
      "label": "Supprimer la clé de sécurité",
      "type": "danger",
      "x": 80.0,
      "y": 62.0,
      "class": "",
      "url": "#"
    },
    {
      "label": "Supprimer cette clé de sécurité U2F",
      "type": "danger",
      "x": 0.0,
      "y": 0.0,
      "class": "",
      "url": "#"
    },
    {
      "label": "Annuler",
      "type": "cancel",
      "x": 28.0,
      "y": 23.0,
      "class": "",
      "url": "/static/web-cloud/account/general.html"
    },
    {
      "label": "Supprimer",
      "type": "danger",
      "x": 140.0,
      "y": 23.0,
      "class": "",
      "url": "#"
    }
  ],
  "sidebar": {
    "type": "account-list",
    "clickable": false,
    "note": "Liste - selection locale uniquement"
  }
}